botdetection/__init__.py
botdetection/__pkginfo__.py
botdetection/_helpers.py
botdetection/config.py
botdetection/http_accept.py
botdetection/http_accept_encoding.py
botdetection/http_accept_language.py
botdetection/http_connection.py
botdetection/http_user_agent.py
botdetection/ip_limit.py
botdetection/ip_lists.py
botdetection/link_token.py
botdetection/redislib.py
botdetection/schema.toml
botdetection-20240226.0.dist-info/LICENSE
botdetection-20240226.0.dist-info/METADATA
botdetection-20240226.0.dist-info/WHEEL
botdetection-20240226.0.dist-info/top_level.txt
botdetection-20240226.0.dist-info/RECORD
