Metadata-Version: 2.1
Name: botdetection
Version: 20240226.0
Summary: Methods for the detection of bots in Flask applications 
Author-email: Markus Heiser <markus.heiser@darmarit.de>
Maintainer-email: Markus Heiser <markus.heiser@darmarit.de>
License: GNU AFFERO GENERAL PUBLIC LICENSE
Project-URL: homepage, https://github.com/searxng/botdetection
Project-URL: repository, https://github.com/searxng/botdetection/
Project-URL: issues, https://github.com/searxng/botdetection/issues
Project-URL: changelog, https://github.com/searxng/botdetection/blob/master/CHANGELOG
Project-URL: documentation, https://searxng.org/botdetection/
Project-URL: #searxng:matrix.org, https://matrix.to/#/#searxng:matrix.org
Keywords: botdetection,flask,SearXNG
Classifier: Development Status :: 5 - Production/Stable
Classifier: Intended Audience :: Developers
Classifier: Topic :: Software Development :: Build Tools
Classifier: License :: OSI Approved :: GNU Affero General Public License v3
Classifier: Programming Language :: Python
Requires-Python: >=3.8
License-File: LICENSE
Requires-Dist: flask
Requires-Dist: pytomlpp
Requires-Dist: redis
Requires-Dist: typing-extensions
Provides-Extra: dev
Requires-Dist: build ; extra == 'dev'
Requires-Dist: Sphinx ; extra == 'dev'
Requires-Dist: sphinx-issues ; extra == 'dev'
Requires-Dist: sphinx-tabs ; extra == 'dev'
Requires-Dist: sphinx-autobuild ; extra == 'dev'
Requires-Dist: sphinx-notfound-page ; extra == 'dev'
Requires-Dist: sphinxcontrib-programoutput ; extra == 'dev'
Requires-Dist: Pallets-Sphinx-Themes ; extra == 'dev'
Requires-Dist: linuxdoc ; extra == 'dev'
Requires-Dist: twine ; extra == 'dev'
Requires-Dist: click ; extra == 'dev'
Provides-Extra: test
Requires-Dist: pylint ; extra == 'test'
